{
  "indexes": [
    {
      "collectionGroup": "users",
      "queryScope": "COLLECTION",
      "fields": [
        {
          "fieldPath": "tier",
          "order": "ASCENDING"
        },
        {
          "fieldPath": "createdAt",
          "order": "DESCENDING"
        }
      ]
    },
    {
      "collectionGroup": "users", 
      "queryScope": "COLLECTION",
      "fields": [
        {
          "fieldPath": "companyId",
          "order": "ASCENDING"
        },
        {
          "fieldPath": "tier",
          "order": "ASCENDING"
        }
      ]
    },
    {
      "collectionGroup": "users",
      "queryScope": "COLLECTION", 
      "fields": [
        {
          "fieldPath": "companyId",
          "order": "ASCENDING"
        },
        {
          "fieldPath": "role",
          "order": "ASCENDING"
        }
      ]
    },
    {
      "collectionGroup": "companies",
      "queryScope": "COLLECTION",
      "fields": [
        {
          "fieldPath": "status",
          "order": "ASCENDING"
        },
        {
          "fieldPath": "createdAt", 
          "order": "DESCENDING"
        }
      ]
    },
    {
      "collectionGroup": "performanceReports",
      "queryScope": "COLLECTION",
      "fields": [
        {
          "fieldPath": "companyId",
          "order": "ASCENDING"
        },
        {
          "fieldPath": "createdAt",
          "order": "DESCENDING"
        }
      ]
    },
    {
      "collectionGroup": "performanceReports",
      "queryScope": "COLLECTION",
      "fields": [
        {
          "fieldPath": "employeeId",
          "order": "ASCENDING"
        },
        {
          "fieldPath": "createdAt",
          "order": "DESCENDING"
        }
      ]
    },
    {
      "collectionGroup": "performanceReports",
      "queryScope": "COLLECTION", 
      "fields": [
        {
          "fieldPath": "companyId",
          "order": "ASCENDING"
        },
        {
          "fieldPath": "status",
          "order": "ASCENDING"
        },
        {
          "fieldPath": "createdAt",
          "order": "DESCENDING"
        }
      ]
    },
    {
      "collectionGroup": "departments",
      "queryScope": "COLLECTION",
      "fields": [
        {
          "fieldPath": "companyId",
          "order": "ASCENDING"
        },
        {
          "fieldPath": "name",
          "order": "ASCENDING"
        }
      ]
    },
    {
      "collectionGroup": "designations",
      "queryScope": "COLLECTION",
      "fields": [
        {
          "fieldPath": "companyId", 
          "order": "ASCENDING"
        },
        {
          "fieldPath": "department",
          "order": "ASCENDING"
        },
        {
          "fieldPath": "level",
          "order": "ASCENDING"
        }
      ]
    },
    {
      "collectionGroup": "comment_notifications",
      "queryScope": "COLLECTION",
      "fields": [
        {
          "fieldPath": "userId",
          "order": "ASCENDING"
        },
        {
          "fieldPath": "read",
          "order": "ASCENDING"
        },
        {
          "fieldPath": "createdAt",
          "order": "DESCENDING"
        }
      ]
    }
  ],
  "fieldOverrides": []
}